LICENSE
MANIFEST.in
README.rst
requirements.txt
setup.py
txinvoke/__init__.py
txinvoke/decorators.py
txinvoke/version.py
txinvoke.egg-info/PKG-INFO
txinvoke.egg-info/SOURCES.txt
txinvoke.egg-info/dependency_links.txt
txinvoke.egg-info/requires.txt
txinvoke.egg-info/top_level.txt