Metadata-Version: 1.1
Name: txinvoke
Version: 0.1.0
Summary: Run inline callbacks from Twisted as Invoke tasks
Home-page: https://github.com/oblalex/txinvoke
Author: Alexander Oblovatniy
Author-email: oblovatniy@gmail.com
License: MIT
Keywords: twisted,invoke,task,callback,deferred,asynchronous
Platform: any
Classifier: Development Status :: 3 - Alpha
Classifier: Intended Audience :: Developers
Classifier: License :: OSI Approved :: MIT License
Classifier: License :: Free for non-commercial use
Classifier: Natural Language :: English
Classifier: Operating System :: OS Independent
Classifier: Topic :: Software Development :: Libraries
Classifier: Topic :: Utilities
Classifier: Framework :: Twisted
